oqs/__init__.py
oqs/oqs.py
oqs/rand.py
oqs/serialize.py
oqs/liboqs.so
pyoqs_wasm-0.15.1.0.dist-info/METADATA
pyoqs_wasm-0.15.1.0.dist-info/WHEEL
pyoqs_wasm-0.15.1.0.dist-info/licenses/LICENSE
pyoqs_wasm-0.15.1.0.dist-info/RECORD
