Metadata-Version: 2.4
Name: pyoqs-wasm
Version: 0.15.1.0
Summary: Pyodide-compatible ctypes interface for Open Quantum Safe liboqs
Project-URL: Homepage, https://github.com/pfeairheller/pyoqs-wasm
Project-URL: Repository, https://github.com/pfeairheller/pyoqs-wasm.git
Author-email: Open Quantum Safe project <contact@openquantumsafe.org>, Evan Asakawa <evanja57@gmail.com>
License:                                  Apache License
License-File: LICENSE
Keywords: cryptography,digital-signatures,kem,liboqs,post-quantum,pyodide,wasm
Classifier: Development Status :: 4 - Beta
Classifier: License :: OSI Approved :: MIT License
Classifier: Programming Language :: Python :: 3
Classifier: Programming Language :: Python :: 3.9
Classifier: Programming Language :: Python :: 3.10
Classifier: Programming Language :: Python :: 3.11
Classifier: Programming Language :: Python :: 3.12
Classifier: Topic :: Security
Classifier: Topic :: Security :: Cryptography
Requires-Python: >=3.9
Requires-Dist: tomli>=2; python_version < '3.11'
Provides-Extra: dev
Requires-Dist: nose2>=0.15.1; extra == 'dev'
Requires-Dist: pytest>=7.0; extra == 'dev'
